lake2bq/__init__.py
lake2bq/cli.py
lake2bq/templates/api.py
lake2bq/templates/oracle.py
lake2bq/utils/__init__.py
lake2bq/utils/generator.py
lake2bq/utils/mappers.py
lake2bq/utils/templates.py
lake2bq-1.6.0.dist-info/METADATA
lake2bq-1.6.0.dist-info/WHEEL
lake2bq-1.6.0.dist-info/entry_points.txt
lake2bq-1.6.0.dist-info/top_level.txt
lake2bq-1.6.0.dist-info/RECORD
